{
  "version": "6",
  "dialect": "sqlite",
  "id": "c4b031de-93cd-4cbf-bf5f-993fe18fb26e",
  "prevId": "00000000-0000-0000-0000-000000000000",
  "tables": {
    "predictions": {
      "name": "predictions",
      "columns": {
        "id": {
          "name": "id",
          "type": "integer",
          "primaryKey": true,
          "notNull": true,
          "autoincrement": true
        },
        "creator_user_id": {
          "name": "creator_user_id",
          "type": "integer",
          "primaryKey": false,
          "notNull": true,
          "autoincrement": false
        },
        "asset_symbol": {
          "name": "asset_symbol",
          "type": "text",
          "primaryKey": false,
          "notNull": true,
          "autoincrement": false
        },
        "direction": {
          "name": "direction",
          "type": "text",
          "primaryKey": false,
          "notNull": true,
          "autoincrement": false
        },
        "timeframe_end": {
          "name": "timeframe_end",
          "type": "integer",
          "primaryKey": false,
          "notNull": true,
          "autoincrement": false
        },
        "confidence": {
          "name": "confidence",
          "type": "integer",
          "primaryKey": false,
          "notNull": true,
          "autoincrement": false
        },
        "status": {
          "name": "status",
          "type": "text",
          "primaryKey": false,
          "notNull": true,
          "autoincrement": false,
          "default": "'open'"
        },
        "settlement_price": {
          "name": "settlement_price",
          "type": "text",
          "primaryKey": false,
          "notNull": false,
          "autoincrement": false
        },
        "settlement_timestamp": {
          "name": "settlement_timestamp",
          "type": "integer",
          "primaryKey": false,
          "notNull": false,
          "autoincrement": false
        },
        "created_at": {
          "name": "created_at",
          "type": "integer",
          "primaryKey": false,
          "notNull": true,
          "autoincrement": false,
          "default": "(unixepoch())"
        }
      },
      "indexes": {
        "predictions_creator_idx": {
          "name": "predictions_creator_idx",
          "columns": [
            "creator_user_id"
          ],
          "isUnique": false
        },
        "predictions_status_idx": {
          "name": "predictions_status_idx",
          "columns": [
            "status"
          ],
          "isUnique": false
        },
        "predictions_timeframe_end_idx": {
          "name": "predictions_timeframe_end_idx",
          "columns": [
            "timeframe_end"
          ],
          "isUnique": false
        }
      },
      "foreignKeys": {
        "predictions_creator_user_id_users_id_fk": {
          "name": "predictions_creator_user_id_users_id_fk",
          "tableFrom": "predictions",
          "tableTo": "users",
          "columnsFrom": [
            "creator_user_id"
          ],
          "columnsTo": [
            "id"
          ],
          "onDelete": "no action",
          "onUpdate": "no action"
        }
      },
      "compositePrimaryKeys": {},
      "uniqueConstraints": {},
      "checkConstraints": {}
    },
    "reputation_events": {
      "name": "reputation_events",
      "columns": {
        "id": {
          "name": "id",
          "type": "integer",
          "primaryKey": true,
          "notNull": true,
          "autoincrement": true
        },
        "user_id": {
          "name": "user_id",
          "type": "integer",
          "primaryKey": false,
          "notNull": true,
          "autoincrement": false
        },
        "prediction_id": {
          "name": "prediction_id",
          "type": "integer",
          "primaryKey": false,
          "notNull": true,
          "autoincrement": false
        },
        "outcome": {
          "name": "outcome",
          "type": "text",
          "primaryKey": false,
          "notNull": true,
          "autoincrement": false
        },
        "delta_score": {
          "name": "delta_score",
          "type": "integer",
          "primaryKey": false,
          "notNull": true,
          "autoincrement": false
        },
        "created_at": {
          "name": "created_at",
          "type": "integer",
          "primaryKey": false,
          "notNull": true,
          "autoincrement": false,
          "default": "(unixepoch())"
        }
      },
      "indexes": {
        "reputation_events_user_idx": {
          "name": "reputation_events_user_idx",
          "columns": [
            "user_id"
          ],
          "isUnique": false
        },
        "reputation_events_prediction_idx": {
          "name": "reputation_events_prediction_idx",
          "columns": [
            "prediction_id"
          ],
          "isUnique": false
        },
        "reputation_events_user_prediction_uniq": {
          "name": "reputation_events_user_prediction_uniq",
          "columns": [
            "user_id",
            "prediction_id"
          ],
          "isUnique": true
        }
      },
      "foreignKeys": {
        "reputation_events_user_id_users_id_fk": {
          "name": "reputation_events_user_id_users_id_fk",
          "tableFrom": "reputation_events",
          "tableTo": "users",
          "columnsFrom": [
            "user_id"
          ],
          "columnsTo": [
            "id"
          ],
          "onDelete": "no action",
          "onUpdate": "no action"
        },
        "reputation_events_prediction_id_predictions_id_fk": {
          "name": "reputation_events_prediction_id_predictions_id_fk",
          "tableFrom": "reputation_events",
          "tableTo": "predictions",
          "columnsFrom": [
            "prediction_id"
          ],
          "columnsTo": [
            "id"
          ],
          "onDelete": "no action",
          "onUpdate": "no action"
        }
      },
      "compositePrimaryKeys": {},
      "uniqueConstraints": {},
      "checkConstraints": {}
    },
    "stakes": {
      "name": "stakes",
      "columns": {
        "id": {
          "name": "id",
          "type": "integer",
          "primaryKey": true,
          "notNull": true,
          "autoincrement": true
        },
        "prediction_id": {
          "name": "prediction_id",
          "type": "integer",
          "primaryKey": false,
          "notNull": true,
          "autoincrement": false
        },
        "user_id": {
          "name": "user_id",
          "type": "integer",
          "primaryKey": false,
          "notNull": true,
          "autoincrement": false
        },
        "side": {
          "name": "side",
          "type": "text",
          "primaryKey": false,
          "notNull": true,
          "autoincrement": false
        },
        "amount": {
          "name": "amount",
          "type": "text",
          "primaryKey": false,
          "notNull": true,
          "autoincrement": false
        },
        "currency": {
          "name": "currency",
          "type": "text",
          "primaryKey": false,
          "notNull": true,
          "autoincrement": false
        },
        "invoice_id": {
          "name": "invoice_id",
          "type": "text",
          "primaryKey": false,
          "notNull": false,
          "autoincrement": false
        },
        "payment_status": {
          "name": "payment_status",
          "type": "text",
          "primaryKey": false,
          "notNull": true,
          "autoincrement": false,
          "default": "'initiated'"
        },
        "created_at": {
          "name": "created_at",
          "type": "integer",
          "primaryKey": false,
          "notNull": true,
          "autoincrement": false,
          "default": "(unixepoch())"
        }
      },
      "indexes": {
        "stakes_invoice_id_uniq": {
          "name": "stakes_invoice_id_uniq",
          "columns": [
            "invoice_id"
          ],
          "isUnique": true
        },
        "stakes_prediction_idx": {
          "name": "stakes_prediction_idx",
          "columns": [
            "prediction_id"
          ],
          "isUnique": false
        },
        "stakes_user_idx": {
          "name": "stakes_user_idx",
          "columns": [
            "user_id"
          ],
          "isUnique": false
        },
        "stakes_user_prediction_side_uniq": {
          "name": "stakes_user_prediction_side_uniq",
          "columns": [
            "user_id",
            "prediction_id",
            "side"
          ],
          "isUnique": true
        }
      },
      "foreignKeys": {
        "stakes_prediction_id_predictions_id_fk": {
          "name": "stakes_prediction_id_predictions_id_fk",
          "tableFrom": "stakes",
          "tableTo": "predictions",
          "columnsFrom": [
            "prediction_id"
          ],
          "columnsTo": [
            "id"
          ],
          "onDelete": "no action",
          "onUpdate": "no action"
        },
        "stakes_user_id_users_id_fk": {
          "name": "stakes_user_id_users_id_fk",
          "tableFrom": "stakes",
          "tableTo": "users",
          "columnsFrom": [
            "user_id"
          ],
          "columnsTo": [
            "id"
          ],
          "onDelete": "no action",
          "onUpdate": "no action"
        }
      },
      "compositePrimaryKeys": {},
      "uniqueConstraints": {},
      "checkConstraints": {}
    },
    "users": {
      "name": "users",
      "columns": {
        "id": {
          "name": "id",
          "type": "integer",
          "primaryKey": true,
          "notNull": true,
          "autoincrement": true
        },
        "alien_subject": {
          "name": "alien_subject",
          "type": "text",
          "primaryKey": false,
          "notNull": true,
          "autoincrement": false
        },
        "created_at": {
          "name": "created_at",
          "type": "integer",
          "primaryKey": false,
          "notNull": true,
          "autoincrement": false,
          "default": "(unixepoch())"
        }
      },
      "indexes": {
        "users_alien_subject_uniq": {
          "name": "users_alien_subject_uniq",
          "columns": [
            "alien_subject"
          ],
          "isUnique": true
        }
      },
      "foreignKeys": {},
      "compositePrimaryKeys": {},
      "uniqueConstraints": {},
      "checkConstraints": {}
    }
  },
  "views": {},
  "enums": {},
  "_meta": {
    "schemas": {},
    "tables": {},
    "columns": {}
  },
  "internal": {
    "indexes": {}
  }
}